{
  "clientName": "Cliente Social Media",
  "proposalType": "Gestão de Redes Sociais",
  "plansDisclaimer": "Atenção: Os planos Plus e Pro podem ser personalizados conforme a demanda. Modificações devem ser alinhadas antes do fechamento e podem alterar o valor final investido.",
  "plans": [
    {
      "name": "Plano Plus",
      "desc": "Constância rotineira com foco em construção gradual de audiência e movimento de vendas.",
      "price": "479",
      "recommended": false,
      "features": [
        "10 Posts Mensais Estratégicos",
        "6 Estáticos (Feed ou Story)",
        "2 Carrosséis Dinâmicos",
        "2 Vídeos (Edição Básica)",
        "Pesquisa de Hashtags e Copy",
        "Básico: Planejamento Mensal"
      ]
    },
    {
      "name": "Plano Pro",
      "desc": "Presença digital agressiva. Dominação de território e conversão de seguidores em clientes reais.",
      "price": "779",
      "recommended": true,
      "features": [
        "16 Posts Mensais de Alto Impacto",
        "10 Estáticos (Feed ou Story)",
        "3 Carrosséis Dinâmicos",
        "3 Vídeos (Edição Básica)",
        "Análise e Otimização de Perfil",
        "Gerenciamento Total de Postagens",
        "Criação de Linha Editorial Master",
        "Relatório Mensal de Desempenho"
      ]
    },
    {
      "name": "Plano Básico",
      "desc": "Manutenção visual essencial para quem está apenas começando a gerar presença na internet.",
      "price": "179",
      "recommended": false,
      "features": [
        "4 Posts Mensais",
        "Formatos Mistos (Feed ou Story)",
        "Legendas Otimizadas p/ Conversão",
        "Organização Básica de Feed"
      ]
    }
  ],
  "bonus": {
    "deadline": "11/05/2026",
    "value": "499,00",
    "items": [
      "Página de Links Personalizada (Bio Site)",
      "2 Posts Premium Adicionais Gratuitos"
    ]
  },
  "processSteps": [
    { 
      "title": "Briefing e Estudo de Perfil", 
      "desc": "Imersão no seu negócio para entender o tom de voz, público-alvo e objetivos exatos nas redes.", 
      "icon": "FileText", 
      "time": "Fase 01" 
    },
    { 
      "title": "Criação da Estratégia", 
      "desc": "Estruturação dos pilares de conteúdo e táticas de venda invisíveis via Instagram.", 
      "icon": "Target", 
      "time": "Fase 02" 
    },
    { 
      "title": "Linha Editorial e Calendário", 
      "desc": "Planejamento prático dos temas e datas para aprovação prévia, com foco em resultados reais.", 
      "icon": "Layout", 
      "time": "Fase 03" 
    },
    { 
      "title": "Início do Alinhamento Visual", 
      "desc": "Produção imersiva das peças gráficas e edições, elevando a sua marca a um nível premium.", 
      "icon": "ShieldCheck", 
      "time": "Fase 04" 
    },
    { 
      "title": "Gerenciamento das Postagens", 
      "desc": "Agendamento e execução do plano. Liberamos o seu tempo para você focar apenas em faturar.", 
      "icon": "Send", 
      "time": "Fase 05" 
    }
  ],
  "mainService": {
    "title": "Gestão de Social Media",
    "desc": "Transformamos seu Instagram em uma máquina de autoridade. Criamos desde a estratégia magnética até o post final, otimizando o seu tempo e profissionalizando a sua vitrine digital.",
    "icon": "Target",
    "tags": ["Estratégia", "Design", "Vídeos", "Copywriting"]
  },
  "secondaryServices": [
    { 
      "title": "Estratégia de Fundo de Funil", 
      "desc": "Posts programados e pensados não só para visualizações, mas para transformar visitantes curiosos em clientes pagantes.", 
      "icon": "Zap" 
    },
    { 
      "title": "Autoridade Perceptível", 
      "desc": "Seu design importa. Elevamos sua estética para você cobrar mais caro e ser respeitado no seu nicho.", 
      "icon": "ShieldCheck" 
    }
  ],
  "strategyService": {
    "title": "Nós executamos de ponta a ponta.",
    "desc": "Diferente de agências tradicionais, somos ágeis e focados em velocidade de adaptação para as novas tendências de mercado e algoritmos.",
    "icon": "Code",
    "hideButton": true
  }
}
